esmerald/__init__.py
esmerald/__main__.py
esmerald/applications.py
esmerald/background.py
esmerald/context.py
esmerald/encoders.py
esmerald/exception_handlers.py
esmerald/exceptions.py
esmerald/injector.py
esmerald/logging.py
esmerald/param_functions.py
esmerald/params.py
esmerald/parsers.py
esmerald/py.typed
esmerald/requests.py
esmerald/staticfiles.py
esmerald/testclient.py
esmerald/types.py
esmerald/typing.py
esmerald/websockets.py
esmerald/conf/__init__.py
esmerald/conf/enums.py
esmerald/conf/global_settings.py
esmerald/conf/directives/__init__.py
esmerald/conf/directives/app_template/__init__.py-tpl
esmerald/conf/directives/app_template/tests.py-tpl
esmerald/conf/directives/app_template/directives/__init__.py-tpl
esmerald/conf/directives/app_template/directives/operations/__init__.py-tpl
esmerald/conf/directives/app_template/{{ api_version }}/__init__.py-tpl
esmerald/conf/directives/app_template/{{ api_version }}/controllers.py-tpl
esmerald/conf/directives/app_template/{{ api_version }}/schemas.py-tpl
esmerald/conf/directives/app_template/{{ api_version }}/urls.py-tpl
esmerald/conf/directives/app_template_context/__init__.py-tpl
esmerald/conf/directives/app_template_context/controllers.py-tpl
esmerald/conf/directives/app_template_context/dtos.py-tpl
esmerald/conf/directives/app_template_context/repository.py-tpl
esmerald/conf/directives/app_template_context/service.py-tpl
esmerald/conf/directives/app_template_context/tests.py-tpl
esmerald/conf/directives/app_template_context/urls.py-tpl
esmerald/conf/directives/app_template_context/directives/__init__.py-tpl
esmerald/conf/directives/app_template_context/directives/operations/__init__.py-tpl
esmerald/conf/directives/deployment_template/docker/Dockerfile.e-tpl
esmerald/conf/directives/deployment_template/gunicorn/gunicorn_conf.py.e-tpl
esmerald/conf/directives/deployment_template/nginx/nginx.conf.e-tpl
esmerald/conf/directives/deployment_template/nginx/nginx.json-logging.conf.e-tpl
esmerald-3.9.4.dist-info/METADATA
esmerald-3.9.4.dist-info/WHEEL
esmerald-3.9.4.dist-info/entry_points.txt
esmerald-3.9.4.dist-info/licenses/LICENSE
esmerald-3.9.4.dist-info/RECORD
